[
    {
        "slide_number": 1,
        "image_index": 1,
        "coordinates": {
            "left": 74.71424865722656,
            "top": 134.54425048828125,
            "width": 127.06275939941406,
            "height": 92.88212585449219,
            "total_width": 720.0,
            "total_height": 540.0
        },
        "image_path": "images/287/image_1.png"
    },
    {
        "slide_number": 1,
        "image_index": 2,
        "coordinates": {
            "left": 540.0352172851562,
            "top": 142.55551147460938,
            "width": 137.3944091796875,
            "height": 76.85945129394531,
            "total_width": 720.0,
            "total_height": 540.0
        },
        "image_path": "images/287/image_2.png"
    },
    {
        "slide_number": 1,
        "image_index": 3,
        "coordinates": {
            "left": 317.0210876464844,
            "top": 273.2219543457031,
            "width": 107.76984405517578,
            "height": 162.80117797851562,
            "total_width": 720.0,
            "total_height": 540.0
        },
        "image_path": "images/287/image_3.png"
    }
]